exhentai/__init__.py
exhentai/client.py
exhentai/downloader.py
exhentai/entity.py
exhentai/module.py
exhentai/option.py
exhentai/toolkit.py
exhentai-0.1.7.dist-info/LICENSE
exhentai-0.1.7.dist-info/METADATA
exhentai-0.1.7.dist-info/WHEEL
exhentai-0.1.7.dist-info/top_level.txt
exhentai-0.1.7.dist-info/RECORD
