Metadata-Version: 2.1
Name: exhentai
Version: 0.1.7
Summary: Python Downloader for exhentai.org
Home-page: https://github.com/hect0x7/exhentai
Author: hect0x7
Author-email: 93357912+hect0x7@users.noreply.github.com
Keywords: python,downloader,nsfw,e-hentai,hentai,exhentai,ehentai
Classifier: Development Status :: 4 - Beta
Classifier: Intended Audience :: Developers
Classifier: Programming Language :: Python :: 3.11
Classifier: Programming Language :: Python :: 3.12
Classifier: Operating System :: MacOS
Classifier: Operating System :: POSIX :: Linux
Classifier: Operating System :: Microsoft :: Windows
Requires-Python: >=3.11
License-File: LICENSE
Requires-Dist: commonX
Requires-Dist: Pillow
Requires-Dist: beautifulsoup4
Requires-Dist: lxml
